openapi_client/__init__.py
openapi_client/api_client.py
openapi_client/api_response.py
openapi_client/configuration.py
openapi_client/exceptions.py
openapi_client/py.typed
openapi_client/rest.py
openapi_client/api/__init__.py
openapi_client/api/branches_api.py
openapi_client/api/healthcheck_api.py
openapi_client/api/key_manager_api.py
openapi_client/api/orders_api.py
openapi_client/api/room_types_api.py
openapi_client/api/rooms_api.py
openapi_client/api/webhooks_manager_api.py
openapi_client/models/__init__.py
openapi_client/models/api_branch_models_key.py
openapi_client/models/api_branch_models_key_input.py
openapi_client/models/api_branch_view_key_responses.py
openapi_client/models/api_key_manager_models_key.py
openapi_client/models/api_key_manager_models_key_input.py
openapi_client/models/api_key_manager_view_key_responses.py
openapi_client/models/guest.py
openapi_client/models/http_validation_error.py
openapi_client/models/id_document.py
openapi_client/models/order.py
openapi_client/models/order_input.py
openapi_client/models/order_responses.py
openapi_client/models/photocopy.py
openapi_client/models/price.py
openapi_client/models/price_max.py
openapi_client/models/price_min.py
openapi_client/models/room.py
openapi_client/models/room_input.py
openapi_client/models/room_responses.py
openapi_client/models/room_type.py
openapi_client/models/room_type_input.py
openapi_client/models/room_type_responses.py
openapi_client/models/stayforge.py
openapi_client/models/validation_error.py
openapi_client/models/validation_error_loc_inner.py
openapi_client/models/webhooks_manager.py
openapi_client/models/webhooks_manager_input.py
openapi_client/models/webhooks_manager_responses.py
stayforge/__init__.py
stayforge/api_client.py
stayforge/api_response.py
stayforge/configuration.py
stayforge/exceptions.py
stayforge/py.typed
stayforge/rest.py
stayforge/apis/__init__.py
stayforge/apis/branches_api.py
stayforge/apis/healthcheck_api.py
stayforge/apis/key_manager_api.py
stayforge-0.0.0.dist-info/LICENSE
stayforge-0.0.0.dist-info/METADATA
stayforge-0.0.0.dist-info/WHEEL
stayforge-0.0.0.dist-info/top_level.txt
stayforge-0.0.0.dist-info/RECORD
