Metadata-Version: 2.1
Name: stayforge
Version: 0.0.0
Summary: Stayforge API
Home-page: https://github.com/tokujun-t/stayforge-python
Author: StayForge Team
Author-email: support@stayforge.io
Keywords: OpenAPI,OpenAPI-Generator,Stayforge API
License-File: LICENSE
Requires-Dist: urllib3<3.0.0,>=1.25.3
Requires-Dist: python-dateutil>=2.8.2
Requires-Dist: pydantic>=2
Requires-Dist: typing-extensions>=4.7.1
